tests/__init__.py
tests/conftest.py
tests/test_converter.py
tests/test_crawler.py
web2markdown/__init__.py
web2markdown/cli.py
web2markdown/converter.py
web2markdown/crawler.py
web2markdown-0.1.1.dist-info/LICENSE
web2markdown-0.1.1.dist-info/METADATA
web2markdown-0.1.1.dist-info/WHEEL
web2markdown-0.1.1.dist-info/entry_points.txt
web2markdown-0.1.1.dist-info/top_level.txt
web2markdown-0.1.1.dist-info/RECORD
